{"tables":[{"name":"Addresses","min_role_read":80,"min_role_write":80,"versioned":true,"provider_name":null,"provider_cfg":null,"ownership_formula":null,"fields":[{"name":"address","label":"Address","is_unique":false,"calculated":false,"stored":false,"expression":null,"type":"String","attributes":{"locale":null,"regexp":"","options":"","max_length":null,"min_length":null,"localizes_field":"","re_invalid_error":""},"required":false,"primary_key":false,"refname":"","description":""},{"name":"apartment","label":"Apartment","is_unique":false,"calculated":false,"stored":false,"expression":null,"type":"String","attributes":{"locale":null,"regexp":"","options":"","max_length":null,"min_length":null,"localizes_field":"","re_invalid_error":""},"required":false,"primary_key":false,"refname":"","description":""},{"name":"city","label":"City","is_unique":false,"calculated":false,"stored":false,"expression":null,"type":"String","attributes":{"locale":null,"regexp":"","options":"","max_length":null,"min_length":null,"localizes_field":"","re_invalid_error":""},"required":false,"primary_key":false,"refname":"","description":""},{"name":"id","label":"ID","is_unique":true,"calculated":false,"stored":false,"expression":null,"type":"Integer","attributes":{},"required":true,"primary_key":true,"refname":"","description":""},{"name":"postal_code","label":"Postal Code","is_unique":false,"calculated":false,"stored":false,"expression":null,"type":"String","attributes":{"locale":null,"regexp":"","options":"","max_length":null,"min_length":null,"localizes_field":"","re_invalid_error":""},"required":false,"primary_key":false,"refname":"","description":""},{"name":"user_key","label":"User Key","is_unique":false,"calculated":false,"stored":false,"expression":null,"type":"Key","reftable_name":"users","attributes":{"on_delete":"Fail","include_fts":false,"summary_field":"email"},"required":false,"primary_key":false,"reftype":"Integer","refname":"id","description":""}],"constraints":[],"ownership_field_name":"user_key"},{"name":"Children","min_role_read":80,"min_role_write":80,"versioned":true,"provider_name":null,"provider_cfg":null,"ownership_formula":null,"fields":[{"name":"birthday","label":"Birthday","is_unique":false,"calculated":false,"stored":false,"expression":null,"type":"Date","attributes":{"default":null},"required":true,"primary_key":false,"refname":"","description":""},{"name":"care_card","label":"Care Card","is_unique":false,"calculated":false,"stored":false,"expression":null,"type":"String","attributes":{"locale":null,"regexp":"","options":"","max_length":null,"min_length":null,"localizes_field":"","re_invalid_error":""},"required":false,"primary_key":false,"refname":"","description":""},{"name":"first_language","label":"First Language","is_unique":false,"calculated":false,"stored":false,"expression":null,"type":"String","attributes":{"locale":null,"regexp":"","options":"English, French","max_length":null,"min_length":null,"localizes_field":"","re_invalid_error":""},"required":false,"primary_key":false,"refname":"","description":""},{"name":"first_name","label":"First Name","is_unique":false,"calculated":false,"stored":false,"expression":null,"type":"String","attributes":{"locale":null,"regexp":"","default":null,"options":"","max_length":null,"min_length":null,"localizes_field":"","re_invalid_error":""},"required":true,"primary_key":false,"refname":"","description":""},{"name":"id","label":"ID","is_unique":true,"calculated":false,"stored":false,"expression":null,"type":"Integer","attributes":{},"required":true,"primary_key":true,"refname":"","description":""},{"name":"last_name","label":"Last Name","is_unique":false,"calculated":false,"stored":false,"expression":null,"type":"String","attributes":{"locale":null,"regexp":"","default":null,"options":"","max_length":null,"min_length":null,"localizes_field":"","re_invalid_error":""},"required":true,"primary_key":false,"refname":"","description":""},{"name":"other_languages","label":"Other Languages","is_unique":false,"calculated":false,"stored":false,"expression":null,"type":"String","attributes":{"locale":null,"regexp":"","options":"","max_length":null,"min_length":null,"localizes_field":"","re_invalid_error":""},"required":false,"primary_key":false,"refname":"","description":""},{"name":"photo","label":"Photo","is_unique":false,"calculated":false,"stored":false,"expression":null,"type":"File","attributes":{"min_role_read":"80","also_delete_file":true,"files_accept_filter":""},"required":false,"primary_key":false,"refname":"","description":""},{"name":"private_care_card","label":"Private Care Card","is_unique":false,"calculated":false,"stored":false,"expression":null,"type":"String","attributes":{"locale":null,"regexp":"","options":"","max_length":null,"min_length":null,"localizes_field":"","re_invalid_error":""},"required":false,"primary_key":false,"refname":"","description":""},{"name":"second_language","label":"Second Language","is_unique":false,"calculated":false,"stored":false,"expression":null,"type":"String","attributes":{"locale":null,"regexp":"","options":"French, English","max_length":null,"min_length":null,"localizes_field":"","re_invalid_error":""},"required":false,"primary_key":false,"refname":"","description":""},{"name":"sex","label":"Sex","is_unique":false,"calculated":false,"stored":false,"expression":null,"type":"String","attributes":{"locale":null,"regexp":"","options":"Female, Male","max_length":null,"min_length":null,"localizes_field":"","re_invalid_error":""},"required":false,"primary_key":false,"refname":"","description":""},{"name":"user_key","label":"User Key","is_unique":false,"calculated":false,"stored":false,"expression":null,"type":"Key","reftable_name":"users","attributes":{"on_delete":"Fail","include_fts":false,"summary_field":"email"},"required":false,"primary_key":false,"reftype":"Integer","refname":"id","description":""}],"constraints":[],"ownership_field_name":"user_key"},{"name":"Health","min_role_read":80,"min_role_write":80,"versioned":true,"provider_name":null,"provider_cfg":null,"ownership_formula":null,"fields":[{"name":"any_allergies","label":"Any allergies?","is_unique":false,"calculated":false,"stored":false,"expression":null,"type":"Bool","attributes":{},"required":false,"primary_key":false,"refname":"","description":"Does your child have any allergies?"},{"name":"diphtheria_tetanus_whooping_cough","label":"Diphtheria Tetanus Whooping cough Date","is_unique":false,"calculated":false,"stored":false,"expression":null,"type":"Date","attributes":{},"required":false,"primary_key":false,"refname":"","description":"Diphtheria Tetanus Whooping cough Date"},{"name":"health_problems","label":"Health problems?","is_unique":false,"calculated":false,"stored":false,"expression":null,"type":"Bool","attributes":{},"required":false,"primary_key":false,"refname":"","description":"Does your child have health problems?"},{"name":"hearing_problems","label":"Hearing problems?","is_unique":false,"calculated":false,"stored":false,"expression":null,"type":"Bool","attributes":{},"required":false,"primary_key":false,"refname":"","description":"Does your child have hearing problems?"},{"name":"id","label":"ID","is_unique":true,"calculated":false,"stored":false,"expression":null,"type":"Integer","attributes":{},"required":true,"primary_key":true,"refname":"","description":""},{"name":"illnesses","label":"Illnesses","is_unique":false,"calculated":false,"stored":false,"expression":null,"type":"String","attributes":{"locale":null,"regexp":"","options":"","max_length":null,"min_length":null,"localizes_field":"","re_invalid_error":""},"required":false,"primary_key":false,"refname":"","description":""},{"name":"measles_mumps_rubella","label":"Measles Mumps Rubella","is_unique":false,"calculated":false,"stored":false,"expression":null,"type":"Date","attributes":{},"required":false,"primary_key":false,"refname":"","description":"Measles Mumps Rubella date"},{"name":"meningitis_date","label":"Meningitis Date","is_unique":false,"calculated":false,"stored":false,"expression":null,"type":"Date","attributes":{},"required":false,"primary_key":false,"refname":"","description":"Meningitis Date"},{"name":"please_specify_the_boxes_checked_yes","label":"Please specify the boxes checked: YES","is_unique":false,"calculated":false,"stored":false,"expression":null,"type":"String","attributes":{"locale":null,"regexp":"","options":"","max_length":null,"min_length":null,"localizes_field":"","re_invalid_error":""},"required":false,"primary_key":false,"refname":"","description":"Please specify the boxes checked: YES"},{"name":"polio_date","label":"Polio date","is_unique":false,"calculated":false,"stored":false,"expression":null,"type":"Date","attributes":{},"required":false,"primary_key":false,"refname":"","description":"Polio date"},{"name":"sight_problems","label":"Sight problems?","is_unique":false,"calculated":false,"stored":false,"expression":null,"type":"Bool","attributes":{},"required":false,"primary_key":false,"refname":"","description":"Does your child have sight problems?"},{"name":"special_diet","label":"Special diet?","is_unique":false,"calculated":false,"stored":false,"expression":null,"type":"Bool","attributes":{},"required":false,"primary_key":false,"refname":"","description":"Does your child have a special diet?"},{"name":"speech_problems","label":"Speech problems?","is_unique":false,"calculated":false,"stored":false,"expression":null,"type":"Bool","attributes":{},"required":false,"primary_key":false,"refname":"","description":"Does your child have speech problems?"},{"name":"take_medication","label":"Take medication?","is_unique":false,"calculated":false,"stored":false,"expression":null,"type":"Bool","attributes":{},"required":false,"primary_key":false,"refname":"","description":"Does your child take medication?"},{"name":"user_key","label":"User Key","is_unique":false,"calculated":false,"stored":false,"expression":null,"type":"Key","reftable_name":"users","attributes":{"on_delete":"Fail","include_fts":false,"summary_field":"email"},"required":false,"primary_key":false,"reftype":"Integer","refname":"id","description":""},{"name":"vaccination","label":"Vaccination","is_unique":false,"calculated":false,"stored":false,"expression":null,"type":"String","attributes":{"locale":null,"regexp":"","options":"Attach a copy of the health record, Indicate vaccination dates below","max_length":null,"min_length":null,"localizes_field":"","re_invalid_error":""},"required":false,"primary_key":false,"refname":"","description":""},{"name":"vaccination_file","label":"Vaccination File","is_unique":false,"calculated":false,"stored":false,"expression":null,"type":"File","attributes":{"min_role_read":"40","also_delete_file":true,"files_accept_filter":""},"required":false,"primary_key":false,"refname":"","description":""}],"constraints":[],"ownership_field_name":"user_key"},{"name":"Parents, Tutors, Emergency","min_role_read":80,"min_role_write":80,"versioned":true,"provider_name":null,"provider_cfg":null,"ownership_formula":null,"fields":[{"name":"cell_phone","label":"Cell Phone","is_unique":false,"calculated":false,"stored":false,"expression":null,"type":"String","attributes":{"locale":null,"regexp":"","options":"","max_length":null,"min_length":null,"localizes_field":"","re_invalid_error":""},"required":false,"primary_key":false,"refname":"","description":""},{"name":"email","label":"Email","is_unique":false,"calculated":false,"stored":false,"expression":null,"type":"String","attributes":{"locale":null,"regexp":"","options":"","max_length":null,"min_length":null,"localizes_field":"","re_invalid_error":""},"required":false,"primary_key":false,"refname":"","description":""},{"name":"emergency","label":"Emergency","is_unique":false,"calculated":false,"stored":false,"expression":null,"type":"Bool","attributes":{},"required":false,"primary_key":false,"refname":"","description":""},{"name":"first_name","label":"First Name","is_unique":false,"calculated":false,"stored":false,"expression":null,"type":"String","attributes":{"locale":null,"regexp":"","default":null,"options":"","max_length":null,"min_length":null,"localizes_field":"","re_invalid_error":""},"required":true,"primary_key":false,"refname":"","description":""},{"name":"home_phone","label":"Home Phone","is_unique":false,"calculated":false,"stored":false,"expression":null,"type":"String","attributes":{"locale":null,"regexp":"","options":"","max_length":null,"min_length":null,"localizes_field":"","re_invalid_error":""},"required":false,"primary_key":false,"refname":"","description":""},{"name":"id","label":"ID","is_unique":true,"calculated":false,"stored":false,"expression":null,"type":"Integer","attributes":{},"required":true,"primary_key":true,"refname":"","description":""},{"name":"last_name","label":"Last Name","is_unique":false,"calculated":false,"stored":false,"expression":null,"type":"String","attributes":{"locale":null,"regexp":"","default":null,"options":"","max_length":null,"min_length":null,"localizes_field":"","re_invalid_error":""},"required":true,"primary_key":false,"refname":"","description":""},{"name":"other_relation","label":"Other Relation","is_unique":false,"calculated":false,"stored":false,"expression":null,"type":"String","attributes":{"locale":null,"regexp":"","options":"","max_length":null,"min_length":null,"localizes_field":"","re_invalid_error":""},"required":false,"primary_key":false,"refname":"","description":"Please Specify"},{"name":"relation","label":"Relation","is_unique":false,"calculated":false,"stored":false,"expression":null,"type":"String","attributes":{"locale":null,"regexp":"","options":"Mother, Father, Grandmother, Grandfather, Guardian","max_length":null,"min_length":null,"localizes_field":"","re_invalid_error":""},"required":false,"primary_key":false,"refname":"","description":""},{"name":"user_key","label":"User Key","is_unique":false,"calculated":false,"stored":false,"expression":null,"type":"Key","reftable_name":"users","attributes":{"on_delete":"Fail","include_fts":false,"summary_field":"email"},"required":false,"primary_key":false,"reftype":"Integer","refname":"id","description":""}],"constraints":[],"ownership_field_name":"user_key"},{"name":"Sign up for Authority","min_role_read":80,"min_role_write":80,"versioned":true,"provider_name":null,"provider_cfg":null,"ownership_formula":null,"fields":[{"name":"acknowledge","label":"Acknowledge","is_unique":false,"calculated":false,"stored":false,"expression":null,"type":"String","attributes":{"locale":null,"regexp":"","default":null,"options":"","max_length":null,"min_length":null,"localizes_field":"","re_invalid_error":""},"required":true,"primary_key":false,"refname":"","description":""},{"name":"authority","label":"Authority","is_unique":false,"calculated":false,"stored":false,"expression":null,"type":"String","attributes":{"locale":null,"regexp":"","options":"","max_length":null,"min_length":null,"localizes_field":"","re_invalid_error":""},"required":false,"primary_key":false,"refname":"","description":""},{"name":"date_signed","label":"Date signed","is_unique":false,"calculated":false,"stored":false,"expression":null,"type":"String","attributes":{"locale":null,"regexp":"","default":null,"options":"","max_length":null,"min_length":null,"localizes_field":"","re_invalid_error":""},"required":true,"primary_key":false,"refname":"","description":""},{"name":"id","label":"ID","is_unique":true,"calculated":false,"stored":false,"expression":null,"type":"Integer","attributes":{},"required":true,"primary_key":true,"refname":"","description":""},{"name":"name","label":"Name","is_unique":false,"calculated":false,"stored":false,"expression":null,"type":"String","attributes":{"locale":null,"regexp":"","default":null,"options":"","max_length":null,"min_length":null,"localizes_field":"","re_invalid_error":""},"required":true,"primary_key":false,"refname":"","description":""},{"name":"signature","label":"Signature","is_unique":false,"calculated":false,"stored":false,"expression":null,"type":"File","attributes":{"locale":null,"regexp":"","default":null,"options":"","max_length":null,"min_length":null,"min_role_read":"1","localizes_field":"","also_delete_file":false,"re_invalid_error":"","files_accept_filter":""},"required":true,"primary_key":false,"refname":"","description":""},{"name":"user_key","label":"User Key","is_unique":false,"calculated":false,"stored":false,"expression":null,"type":"Key","reftable_name":"users","attributes":{"on_delete":"Fail","include_fts":false,"summary_field":"email"},"required":false,"primary_key":false,"reftype":"Integer","refname":"id","description":""}],"constraints":[],"ownership_field_name":"user_key"},{"name":"Sign up for Registration","min_role_read":80,"min_role_write":80,"versioned":true,"provider_name":null,"provider_cfg":null,"ownership_formula":null,"fields":[{"name":"acknowledgement","label":"Acknowledgement","is_unique":false,"calculated":false,"stored":false,"expression":null,"type":"String","attributes":{"locale":null,"regexp":"","options":"","max_length":null,"min_length":null,"localizes_field":"","re_invalid_error":""},"required":false,"primary_key":false,"refname":"","description":""},{"name":"date","label":"Date","is_unique":false,"calculated":false,"stored":false,"expression":null,"type":"Date","attributes":{"default":null},"required":true,"primary_key":false,"refname":"","description":""},{"name":"id","label":"ID","is_unique":true,"calculated":false,"stored":false,"expression":null,"type":"Integer","attributes":{},"required":true,"primary_key":true,"refname":"","description":""},{"name":"name","label":"Name","is_unique":false,"calculated":false,"stored":false,"expression":null,"type":"String","attributes":{"locale":null,"regexp":"","default":null,"options":"","max_length":null,"min_length":null,"localizes_field":"","re_invalid_error":""},"required":true,"primary_key":false,"refname":"","description":""},{"name":"service_year","label":"Service Year","is_unique":false,"calculated":false,"stored":false,"expression":null,"type":"String","attributes":{"locale":null,"regexp":"","options":"2023/2024, 2024/2025, 2025/2026, 2026/2027, 2027/2028, 2028/2029, 2029/2030","max_length":null,"min_length":null,"localizes_field":"","re_invalid_error":""},"required":false,"primary_key":false,"refname":"","description":""},{"name":"signature","label":"Signature","is_unique":false,"calculated":false,"stored":false,"expression":null,"type":"File","attributes":{"locale":null,"regexp":"","default":null,"options":"","max_length":null,"min_length":null,"min_role_read":"1","localizes_field":"","also_delete_file":false,"re_invalid_error":"","files_accept_filter":""},"required":true,"primary_key":false,"refname":"","description":""},{"name":"user_key","label":"User Key","is_unique":false,"calculated":false,"stored":false,"expression":null,"type":"Key","reftable_name":"users","attributes":{"on_delete":"Fail","include_fts":false,"summary_field":"email"},"required":false,"primary_key":false,"reftype":"Integer","refname":"id","description":""}],"constraints":[],"ownership_field_name":"user_key"},{"name":"Specialists","min_role_read":80,"min_role_write":80,"versioned":true,"provider_name":null,"provider_cfg":null,"ownership_formula":null,"fields":[{"name":"cell_phone","label":"Cell Phone","is_unique":false,"calculated":false,"stored":false,"expression":null,"type":"String","attributes":{"locale":null,"regexp":"","options":"","max_length":null,"min_length":null,"localizes_field":"","re_invalid_error":""},"required":false,"primary_key":false,"refname":"","description":""},{"name":"id","label":"ID","is_unique":true,"calculated":false,"stored":false,"expression":null,"type":"Integer","attributes":{},"required":true,"primary_key":true,"refname":"","description":""},{"name":"name","label":"Name","is_unique":false,"calculated":false,"stored":false,"expression":null,"type":"String","attributes":{"locale":null,"regexp":"","options":"","max_length":null,"min_length":null,"localizes_field":"","re_invalid_error":""},"required":false,"primary_key":false,"refname":"","description":""},{"name":"other_phone","label":"Other Phone","is_unique":false,"calculated":false,"stored":false,"expression":null,"type":"String","attributes":{"locale":null,"regexp":"","options":"","max_length":null,"min_length":null,"localizes_field":"","re_invalid_error":""},"required":false,"primary_key":false,"refname":"","description":""},{"name":"specialty","label":"Specialty","is_unique":false,"calculated":false,"stored":false,"expression":null,"type":"String","attributes":{"locale":null,"regexp":"","options":"","max_length":null,"min_length":null,"localizes_field":"","re_invalid_error":""},"required":false,"primary_key":false,"refname":"","description":""},{"name":"user_key","label":"User Key","is_unique":false,"calculated":false,"stored":false,"expression":null,"type":"Key","reftable_name":"users","attributes":{"on_delete":"Fail","include_fts":false,"summary_field":"email"},"required":false,"primary_key":false,"reftype":"Integer","refname":"id","description":""},{"name":"work_phone","label":"Work Phone","is_unique":false,"calculated":false,"stored":false,"expression":null,"type":"String","attributes":{"locale":null,"regexp":"","options":"","max_length":null,"min_length":null,"localizes_field":"","re_invalid_error":""},"required":false,"primary_key":false,"refname":"","description":""}],"constraints":[],"ownership_field_name":"user_key"},{"name":"users","min_role_read":1,"min_role_write":1,"versioned":false,"provider_name":null,"provider_cfg":null,"ownership_formula":null,"fields":[{"name":"email","label":"Email","is_unique":true,"calculated":false,"stored":false,"expression":null,"type":"String","attributes":{},"required":true,"primary_key":false,"refname":"","description":""},{"name":"id","label":"ID","is_unique":true,"calculated":false,"stored":false,"expression":null,"type":"Integer","attributes":{},"required":true,"primary_key":true,"refname":"","description":""}],"constraints":[],"ownership_field_name":null},{"name":"Work Contact","min_role_read":80,"min_role_write":80,"versioned":true,"provider_name":null,"provider_cfg":null,"ownership_formula":null,"fields":[{"name":"id","label":"ID","is_unique":true,"calculated":false,"stored":false,"expression":null,"type":"Integer","attributes":{},"required":true,"primary_key":true,"refname":"","description":""},{"name":"user_key","label":"User Key","is_unique":false,"calculated":false,"stored":false,"expression":null,"type":"Key","reftable_name":"users","attributes":{"on_delete":"Fail","include_fts":false,"summary_field":"email"},"required":false,"primary_key":false,"reftype":"Integer","refname":"id","description":""},{"name":"work_email","label":"Work Email","is_unique":false,"calculated":false,"stored":false,"expression":null,"type":"String","attributes":{"locale":null,"regexp":"","options":"","max_length":null,"min_length":null,"localizes_field":"","re_invalid_error":""},"required":false,"primary_key":false,"refname":"","description":""},{"name":"work_hours","label":"Work hours","is_unique":false,"calculated":false,"stored":false,"expression":null,"type":"String","attributes":{"locale":null,"regexp":"","options":"","max_length":null,"min_length":null,"localizes_field":"","re_invalid_error":""},"required":false,"primary_key":false,"refname":"","description":""},{"name":"work_phone","label":"Work Phone 1","is_unique":false,"calculated":false,"stored":false,"expression":null,"type":"String","attributes":{"locale":null,"regexp":"","options":"","max_length":null,"min_length":null,"localizes_field":"","re_invalid_error":""},"required":false,"primary_key":false,"refname":"","description":""},{"name":"work_phone_2","label":"Work Phone 2","is_unique":false,"calculated":false,"stored":false,"expression":null,"type":"String","attributes":{"locale":null,"regexp":"","options":"","max_length":null,"min_length":null,"localizes_field":"","re_invalid_error":""},"required":false,"primary_key":false,"refname":"","description":""},{"name":"workplace","label":"Workplace","is_unique":false,"calculated":false,"stored":false,"expression":null,"type":"String","attributes":{"locale":null,"regexp":"","options":"","max_length":null,"min_length":null,"localizes_field":"","re_invalid_error":""},"required":false,"primary_key":false,"refname":"","description":""}],"constraints":[],"ownership_field_name":"user_key"}],"views":[{"name":"Add Children","viewtemplate":"Edit","configuration":{"id":15,"fixed":{"user_key":null,"preset_user_key":"LoggedIn"},"layout":{"above":[{"gx":null,"gy":null,"style":{"margin-bottom":"1.5rem"},"aligns":["end","start"],"widths":[2,10],"besides":[{"above":[null,{"font":"","type":"blank","block":false,"style":{},"inline":false,"contents":"First Name","labelFor":"first_name","isFormula":{},"textStyle":""}]},{"above":[null,{"type":"field","block":false,"fieldview":"edit","textStyle":"","field_name":"first_name","configuration":{}}]}],"breakpoints":["",""]},{"gx":null,"gy":null,"style":{"margin-bottom":"1.5rem"},"aligns":["end","start"],"widths":[2,10],"besides":[{"above":[null,{"font":"","type":"blank","block":false,"style":{},"inline":false,"contents":"Last Name","labelFor":"last_name","isFormula":{},"textStyle":""}]},{"above":[null,{"type":"field","block":false,"fieldview":"edit","textStyle":"","field_name":"last_name","configuration":{}}]}],"breakpoints":["",""]},{"gx":null,"gy":null,"style":{"margin-bottom":"1.5rem"},"aligns":["end","start"],"widths":[2,10],"besides":[{"above":[null,{"font":"","type":"blank","block":false,"style":{},"inline":false,"contents":"Sex","labelFor":"sex","isFormula":{},"textStyle":""}]},{"above":[null,{"type":"field","block":false,"fieldview":"edit","textStyle":"","field_name":"sex","configuration":{}}]}],"breakpoints":["",""]},{"gx":null,"gy":null,"style":{"margin-bottom":"1.5rem"},"aligns":["end","start"],"widths":[2,10],"besides":[{"above":[null,{"font":"","type":"blank","block":false,"style":{},"inline":false,"contents":"Photo","labelFor":"photo","isFormula":{},"textStyle":""}]},{"above":[null,{"type":"field","block":false,"fieldview":"upload","textStyle":"","field_name":"photo","configuration":{}}]}],"breakpoints":["",""]},{"gx":null,"gy":null,"style":{"margin-bottom":"1.5rem"},"aligns":["end","start"],"widths":[2,10],"besides":[{"above":[null,{"font":"","type":"blank","block":false,"style":{},"inline":false,"contents":"Birthday","labelFor":"birthday","isFormula":{},"textStyle":""}]},{"above":[null,{"type":"field","block":false,"fieldview":"flatpickr","textStyle":"","field_name":"birthday","configuration":{"locale":"","day_only":true,"dateFormat":"Y-m-d"}}]}],"breakpoints":["",""]},{"gx":null,"gy":null,"style":{"margin-bottom":"1.5rem"},"aligns":["end","start"],"widths":[2,10],"besides":[{"above":[null,{"font":"","type":"blank","block":false,"style":{},"inline":false,"contents":"Care Card","labelFor":"care_card","isFormula":{},"textStyle":""}]},{"above":[null,{"type":"field","block":false,"fieldview":"edit","textStyle":"","field_name":"care_card","configuration":{}}]}],"breakpoints":["",""]},{"gx":null,"gy":null,"style":{"margin-bottom":"1.5rem"},"aligns":["end","start"],"widths":[2,10],"besides":[{"above":[null,{"font":"","type":"blank","block":false,"style":{},"inline":false,"contents":"Private Care Card","labelFor":"private_care_card","isFormula":{},"textStyle":""}]},{"above":[null,{"type":"field","block":false,"fieldview":"edit","textStyle":"","field_name":"private_care_card","configuration":{}}]}],"breakpoints":["",""]},{"gx":null,"gy":null,"style":{"margin-bottom":"1.5rem"},"aligns":["end","start"],"widths":[2,10],"besides":[{"above":[null,{"font":"","type":"blank","block":false,"style":{},"inline":false,"contents":"First Language","labelFor":"first_language","isFormula":{},"textStyle":""}]},{"above":[null,{"type":"field","block":false,"fieldview":"edit","textStyle":"","field_name":"first_language","configuration":{}}]}],"breakpoints":["",""]},{"gx":null,"gy":null,"style":{"margin-bottom":"1.5rem"},"aligns":["end","start"],"widths":[2,10],"besides":[{"above":[null,{"font":"","type":"blank","block":false,"style":{},"inline":false,"contents":"Second Language","labelFor":"second_language","isFormula":{},"textStyle":""}]},{"above":[null,{"type":"field","block":false,"fieldview":"edit","textStyle":"","field_name":"second_language","configuration":{}}]}],"breakpoints":["",""]},{"gx":null,"gy":null,"style":{"margin-bottom":"1.5rem"},"aligns":["end","start"],"widths":[2,10],"besides":[{"above":[null,{"font":"","type":"blank","block":false,"style":{},"inline":false,"contents":"Other Languages","labelFor":"other_languages","isFormula":{},"textStyle":""}]},{"above":[null,{"type":"field","block":false,"fieldview":"edit","textStyle":"","field_name":"other_languages","configuration":{}}]}],"breakpoints":["",""]},{"type":"action","block":false,"rndid":"c327c2","minRole":100,"isFormula":{},"action_icon":"","action_name":"Save","action_size":"","action_bgcol":"","action_label":"","action_style":"btn-primary","configuration":{},"action_textcol":"","action_bordercol":""}]},"columns":[{"type":"Field","block":false,"fieldview":"edit","textStyle":"","field_name":"first_name","configuration":{}},{"type":"Field","block":false,"fieldview":"edit","textStyle":"","field_name":"last_name","configuration":{}},{"type":"Field","block":false,"fieldview":"edit","textStyle":"","field_name":"sex","configuration":{}},{"type":"Field","block":false,"fieldview":"upload","textStyle":"","field_name":"photo","configuration":{}},{"type":"Field","block":false,"fieldview":"flatpickr","textStyle":"","field_name":"birthday","configuration":{"locale":"","day_only":true,"dateFormat":"Y-m-d"}},{"type":"Field","block":false,"fieldview":"edit","textStyle":"","field_name":"care_card","configuration":{}},{"type":"Field","block":false,"fieldview":"edit","textStyle":"","field_name":"private_care_card","configuration":{}},{"type":"Field","block":false,"fieldview":"edit","textStyle":"","field_name":"first_language","configuration":{}},{"type":"Field","block":false,"fieldview":"edit","textStyle":"","field_name":"second_language","configuration":{}},{"type":"Field","block":false,"fieldview":"edit","textStyle":"","field_name":"other_languages","configuration":{}},{"type":"Action","rndid":"c327c2","minRole":100,"isFormula":{},"action_icon":"","action_name":"Save","action_size":"","action_bgcol":"","action_label":"","action_style":"btn-primary","configuration":{},"action_textcol":"","action_bordercol":""}],"viewname":"Add Children","auto_save":false,"split_paste":false,"exttable_name":null,"page_when_done":null,"view_when_done":null,"dest_url_formula":null,"destination_type":"Back to referer","formula_destinations":[]},"min_role":80,"table":"Children","slug":{"label":"","steps":[]},"attributes":{"popup_title":"Add Children","popup_width":50,"popup_width_units":"%","popup_save_indicator":false},"default_render_page":"","exttable_name":null},{"name":"Children","viewtemplate":"List","configuration":{"id":12,"layout":{"above":[null,{"style":{"margin-bottom":"1.5rem"},"aligns":["end","start"],"widths":[2,10],"besides":[{"above":[null,{"type":"blank","block":false,"contents":"Birthday","textStyle":""}]},{"above":[null,{"type":"field","block":false,"fieldview":"show","textStyle":"","field_name":"birthday"}]}]},{"style":{"margin-bottom":"1.5rem"},"aligns":["end","start"],"widths":[2,10],"besides":[{"above":[null,{"type":"blank","block":false,"contents":"Care Card","textStyle":""}]},{"above":[null,{"type":"field","block":false,"fieldview":"as_text","textStyle":"","field_name":"care_card"}]}]},{"style":{"margin-bottom":"1.5rem"},"aligns":["end","start"],"widths":[2,10],"besides":[{"above":[null,{"type":"blank","block":false,"contents":"First Language","textStyle":""}]},{"above":[null,{"type":"field","block":false,"fieldview":"as_text","textStyle":"","field_name":"first_language"}]}]},{"style":{"margin-bottom":"1.5rem"},"aligns":["end","start"],"widths":[2,10],"besides":[{"above":[null,{"type":"blank","block":false,"contents":"First Name","textStyle":""}]},{"above":[null,{"type":"field","block":false,"fieldview":"as_text","textStyle":"","field_name":"first_name"}]}]},{"style":{"margin-bottom":"1.5rem"},"aligns":["end","start"],"widths":[2,10],"besides":[{"above":[null,{"type":"blank","block":false,"contents":"Last Name","textStyle":""}]},{"above":[null,{"type":"field","block":false,"fieldview":"as_text","textStyle":"","field_name":"last_name"}]}]},{"style":{"margin-bottom":"1.5rem"},"aligns":["end","start"],"widths":[2,10],"besides":[{"above":[null,{"type":"blank","block":false,"contents":"Other Languages","textStyle":""}]},{"above":[null,{"type":"field","block":false,"fieldview":"as_text","textStyle":"","field_name":"other_languages"}]}]},{"style":{"margin-bottom":"1.5rem"},"aligns":["end","start"],"widths":[2,10],"besides":[{"above":[null,{"type":"blank","block":false,"contents":"Photo","textStyle":""}]},{"above":[null,{"type":"field","block":false,"fieldview":"Download link","textStyle":"","field_name":"photo"}]}]},{"style":{"margin-bottom":"1.5rem"},"aligns":["end","start"],"widths":[2,10],"besides":[{"above":[null,{"type":"blank","block":false,"contents":"Private Care Card","textStyle":""}]},{"above":[null,{"type":"field","block":false,"fieldview":"as_text","textStyle":"","field_name":"private_care_card"}]}]},{"style":{"margin-bottom":"1.5rem"},"aligns":["end","start"],"widths":[2,10],"besides":[{"above":[null,{"type":"blank","block":false,"contents":"Second Language","textStyle":""}]},{"above":[null,{"type":"field","block":false,"fieldview":"as_text","textStyle":"","field_name":"second_language"}]}]},{"style":{"margin-bottom":"1.5rem"},"aligns":["end","start"],"widths":[2,10],"besides":[{"above":[null,{"type":"blank","block":false,"contents":"Sex","textStyle":""}]},{"above":[null,{"type":"field","block":false,"fieldview":"as_text","textStyle":"","field_name":"sex"}]}]}]},"columns":[{"type":"Field","title":"","fieldview":"as_text","_columndef":"{\"type\":\"Field\",\"title\":\"\",\"fieldview\":\"as_text\",\"_columndef\":\"{\\\"type\\\":\\\"Field\\\",\\\"title\\\":\\\"\\\",\\\"fieldview\\\":\\\"as_text\\\",\\\"_columndef\\\":\\\"{\\\\\\\"type\\\\\\\":\\\\\\\"Field\\\\\\\",\\\\\\\"title\\\\\\\":\\\\\\\"\\\\\\\",\\\\\\\"fieldview\\\\\\\":\\\\\\\"as_text\\\\\\\",\\\\\\\"field_name\\\\\\\":\\\\\\\"first_name\\\\\\\"}\\\",\\\"field_name\\\":\\\"first_name\\\"}\",\"field_name\":\"first_name\"}","field_name":"first_name"},{"type":"Field","title":"","fieldview":"as_text","_columndef":"{\"type\":\"Field\",\"title\":\"\",\"fieldview\":\"as_text\",\"_columndef\":\"{\\\"type\\\":\\\"Field\\\",\\\"title\\\":\\\"\\\",\\\"fieldview\\\":\\\"as_text\\\",\\\"_columndef\\\":\\\"{\\\\\\\"type\\\\\\\":\\\\\\\"Field\\\\\\\",\\\\\\\"title\\\\\\\":\\\\\\\"\\\\\\\",\\\\\\\"fieldview\\\\\\\":\\\\\\\"as_text\\\\\\\",\\\\\\\"field_name\\\\\\\":\\\\\\\"last_name\\\\\\\"}\\\",\\\"field_name\\\":\\\"last_name\\\"}\",\"field_name\":\"last_name\"}","field_name":"last_name"},{"type":"Field","title":"","format":"YYYYMMDD","alignment":"","col_width":"","fieldview":"format","_columndef":"{\"type\":\"Field\",\"title\":\"\",\"format\":\"YYYYMMDD\",\"alignment\":\"\",\"col_width\":\"\",\"fieldview\":\"format\",\"_columndef\":\"{\\\"type\\\":\\\"Field\\\",\\\"title\\\":\\\"\\\",\\\"alignment\\\":\\\"\\\",\\\"col_width\\\":\\\"\\\",\\\"fieldview\\\":\\\"format\\\",\\\"_columndef\\\":\\\"{\\\\\\\"type\\\\\\\":\\\\\\\"Field\\\\\\\",\\\\\\\"title\\\\\\\":\\\\\\\"\\\\\\\",\\\\\\\"alignment\\\\\\\":\\\\\\\"\\\\\\\",\\\\\\\"col_width\\\\\\\":\\\\\\\"\\\\\\\",\\\\\\\"fieldview\\\\\\\":\\\\\\\"showDay\\\\\\\",\\\\\\\"field_name\\\\\\\":\\\\\\\"birthday\\\\\\\",\\\\\\\"header_label\\\\\\\":\\\\\\\"\\\\\\\",\\\\\\\"click_to_edit\\\\\\\":\\\\\\\"\\\\\\\"}\\\",\\\"field_name\\\":\\\"birthday\\\",\\\"header_label\\\":\\\"\\\",\\\"click_to_edit\\\":\\\"on\\\",\\\"format\\\":\\\"YYYY-MM-DD\\\"}\",\"field_name\":\"birthday\",\"header_label\":\"\",\"click_to_edit\":\"\"}","field_name":"birthday","header_label":"","click_to_edit":""},{"type":"Field","title":"","fieldview":"as_text","_columndef":"{\"type\":\"Field\",\"title\":\"\",\"fieldview\":\"as_text\",\"_columndef\":\"{\\\"type\\\":\\\"Field\\\",\\\"title\\\":\\\"\\\",\\\"fieldview\\\":\\\"as_text\\\",\\\"_columndef\\\":\\\"{\\\\\\\"type\\\\\\\":\\\\\\\"Field\\\\\\\",\\\\\\\"title\\\\\\\":\\\\\\\"\\\\\\\",\\\\\\\"fieldview\\\\\\\":\\\\\\\"as_text\\\\\\\",\\\\\\\"field_name\\\\\\\":\\\\\\\"sex\\\\\\\"}\\\",\\\"field_name\\\":\\\"sex\\\"}\",\"field_name\":\"sex\"}","field_name":"sex"},{"type":"Field","title":"","alignment":"","col_width":"","fieldview":"Thumbnail","_columndef":"{\"type\":\"Field\",\"title\":\"\",\"alignment\":\"\",\"col_width\":\"\",\"fieldview\":\"Thumbnail\",\"_columndef\":\"{\\\"type\\\":\\\"Field\\\",\\\"title\\\":\\\"\\\",\\\"alignment\\\":\\\"\\\",\\\"col_width\\\":\\\"\\\",\\\"fieldview\\\":\\\"Thumbnail\\\",\\\"_columndef\\\":\\\"{\\\\\\\"type\\\\\\\":\\\\\\\"Field\\\\\\\",\\\\\\\"title\\\\\\\":\\\\\\\"\\\\\\\",\\\\\\\"width\\\\\\\":\\\\\\\"\\\\\\\",\\\\\\\"expand\\\\\\\":\\\\\\\"\\\\\\\",\\\\\\\"height\\\\\\\":\\\\\\\"\\\\\\\",\\\\\\\"alignment\\\\\\\":\\\\\\\"\\\\\\\",\\\\\\\"col_width\\\\\\\":\\\\\\\"\\\\\\\",\\\\\\\"fieldview\\\\\\\":\\\\\\\"Thumbnail\\\\\\\",\\\\\\\"field_name\\\\\\\":\\\\\\\"photo\\\\\\\",\\\\\\\"header_label\\\\\\\":\\\\\\\"\\\\\\\",\\\\\\\"click_to_edit\\\\\\\":\\\\\\\"on\\\\\\\"}\\\",\\\"field_name\\\":\\\"photo\\\",\\\"header_label\\\":\\\"\\\",\\\"click_to_edit\\\":\\\"on\\\"}\",\"field_name\":\"photo\",\"header_label\":\"\",\"click_to_edit\":\"on\"}","field_name":"photo","header_label":"","click_to_edit":"on"},{"type":"Field","title":"","fieldview":"as_text","_columndef":"{\"type\":\"Field\",\"title\":\"\",\"fieldview\":\"as_text\",\"_columndef\":\"{\\\"type\\\":\\\"Field\\\",\\\"title\\\":\\\"\\\",\\\"fieldview\\\":\\\"as_text\\\",\\\"_columndef\\\":\\\"{\\\\\\\"type\\\\\\\":\\\\\\\"Field\\\\\\\",\\\\\\\"title\\\\\\\":\\\\\\\"\\\\\\\",\\\\\\\"fieldview\\\\\\\":\\\\\\\"as_text\\\\\\\",\\\\\\\"field_name\\\\\\\":\\\\\\\"care_card\\\\\\\"}\\\",\\\"field_name\\\":\\\"care_card\\\"}\",\"field_name\":\"care_card\"}","field_name":"care_card"},{"type":"Field","title":"","fieldview":"as_text","_columndef":"{\"type\":\"Field\",\"title\":\"\",\"fieldview\":\"as_text\",\"_columndef\":\"{\\\"type\\\":\\\"Field\\\",\\\"title\\\":\\\"\\\",\\\"fieldview\\\":\\\"as_text\\\",\\\"_columndef\\\":\\\"{\\\\\\\"type\\\\\\\":\\\\\\\"Field\\\\\\\",\\\\\\\"title\\\\\\\":\\\\\\\"\\\\\\\",\\\\\\\"fieldview\\\\\\\":\\\\\\\"as_text\\\\\\\",\\\\\\\"field_name\\\\\\\":\\\\\\\"private_care_card\\\\\\\"}\\\",\\\"field_name\\\":\\\"private_care_card\\\"}\",\"field_name\":\"private_care_card\"}","field_name":"private_care_card"},{"type":"Field","title":"","fieldview":"as_text","_columndef":"{\"type\":\"Field\",\"title\":\"\",\"fieldview\":\"as_text\",\"_columndef\":\"{\\\"type\\\":\\\"Field\\\",\\\"title\\\":\\\"\\\",\\\"fieldview\\\":\\\"as_text\\\",\\\"_columndef\\\":\\\"{\\\\\\\"type\\\\\\\":\\\\\\\"Field\\\\\\\",\\\\\\\"title\\\\\\\":\\\\\\\"\\\\\\\",\\\\\\\"fieldview\\\\\\\":\\\\\\\"as_text\\\\\\\",\\\\\\\"field_name\\\\\\\":\\\\\\\"first_language\\\\\\\"}\\\",\\\"field_name\\\":\\\"first_language\\\"}\",\"field_name\":\"first_language\"}","field_name":"first_language"},{"type":"Field","title":"","fieldview":"as_text","_columndef":"{\"type\":\"Field\",\"title\":\"\",\"fieldview\":\"as_text\",\"_columndef\":\"{\\\"type\\\":\\\"Field\\\",\\\"title\\\":\\\"\\\",\\\"fieldview\\\":\\\"as_text\\\",\\\"_columndef\\\":\\\"{\\\\\\\"type\\\\\\\":\\\\\\\"Field\\\\\\\",\\\\\\\"title\\\\\\\":\\\\\\\"\\\\\\\",\\\\\\\"fieldview\\\\\\\":\\\\\\\"as_text\\\\\\\",\\\\\\\"field_name\\\\\\\":\\\\\\\"second_language\\\\\\\"}\\\",\\\"field_name\\\":\\\"second_language\\\"}\",\"field_name\":\"second_language\"}","field_name":"second_language"},{"type":"Field","title":"","fieldview":"as_text","_columndef":"{\"type\":\"Field\",\"title\":\"\",\"fieldview\":\"as_text\",\"_columndef\":\"{\\\"type\\\":\\\"Field\\\",\\\"title\\\":\\\"\\\",\\\"fieldview\\\":\\\"as_text\\\",\\\"_columndef\\\":\\\"{\\\\\\\"type\\\\\\\":\\\\\\\"Field\\\\\\\",\\\\\\\"title\\\\\\\":\\\\\\\"\\\\\\\",\\\\\\\"fieldview\\\\\\\":\\\\\\\"as_text\\\\\\\",\\\\\\\"field_name\\\\\\\":\\\\\\\"other_languages\\\\\\\"}\\\",\\\"field_name\\\":\\\"other_languages\\\"}\",\"field_name\":\"other_languages\"}","field_name":"other_languages"}],"viewname":"Children","default_state":{"id":null,"sex":"","photo":null,"birthday":null,"user_key":"Preset:LoggedIn","care_card":"","last_name":"","transpose":false,"first_name":"","_descending":false,"include_fml":"","_omit_header":false,"_order_field":"first_name","_rows_per_page":20,"first_language":"","_create_db_view":false,"other_languages":"","second_language":"","transpose_width":null,"hide_null_columns":false,"private_care_card":"","transpose_width_units":null},"exttable_name":null,"view_to_create":"Add Children","create_link_size":"","create_link_style":"btn btn-primary","create_view_label":"Create","create_view_display":"Popup","create_view_location":"Bottom right"},"min_role":80,"table":"Children","slug":{"label":"","steps":[]},"attributes":{"popup_title":"","popup_width":null,"popup_width_units":null,"popup_save_indicator":false},"default_render_page":"","exttable_name":null}],"plugins":[{"name":"base","source":"npm","location":"@saltcorn/base-plugin","configuration":null,"deploy_private_key":null},{"name":"sbadmin2","source":"npm","location":"@saltcorn/sbadmin2","configuration":null,"deploy_private_key":null},{"name":"flatpickr-date","source":"npm","location":"@saltcorn/flatpickr-date","configuration":null,"deploy_private_key":null},{"name":"fullcalendar","source":"npm","location":"@saltcorn/fullcalendar","configuration":null,"deploy_private_key":null},{"name":"captcha","source":"npm","location":"@saltcorn/captcha","configuration":null,"deploy_private_key":null},{"name":"@saltcorn/html","source":"npm","location":"@saltcorn/html","configuration":null,"deploy_private_key":null},{"name":"ckeditor4","source":"npm","location":"@saltcorn/ckeditor4","configuration":null,"deploy_private_key":null},{"name":"kanban","source":"npm","location":"@saltcorn/kanban","configuration":null,"deploy_private_key":null},{"name":"page-to-pdf","source":"npm","location":"@saltcorn/page-to-pdf","configuration":null,"deploy_private_key":null},{"name":"markdown","source":"npm","location":"@saltcorn/markdown","configuration":null,"deploy_private_key":null},{"name":"signature-pad","source":"npm","location":"@saltcorn/signature-pad","configuration":null,"deploy_private_key":null},{"name":"any-bootstrap-theme","source":"npm","location":"@saltcorn/any-bootstrap-theme","configuration":{"fluid":false,"theme":"flatly","toppad":5,"css_url":null,"in_card":false,"css_file":null,"fixedTop":true,"menu_style":"Top Navbar","colorscheme":"navbar-dark bg-dark","css_integrity":null,"backgroundColor":"#ffffff"},"deploy_private_key":null}],"pages":[{"name":"homepage","title":"CCMS home page - The Child Care Management System","description":"CCMS home page - The Child Care Management System","min_role":100,"layout":{"above":[{"font":"","type":"blank","block":false,"style":{},"inline":false,"contents":"","labelFor":"","isFormula":{},"textStyle":""},{"font":"","icon":"","type":"blank","block":false,"style":{},"inline":false,"contents":"Hello world","labelFor":"","isFormula":{},"textStyle":""},{"gx":null,"gy":null,"style":{},"widths":[6,6],"besides":[null,null],"breakpoints":["sm","sm"]},{"type":"line_break"}]},"fixed_states":{},"menu_label":"Inscription","root_page_for_roles":[]}],"roles":[{"id":100,"role":"public"},{"id":80,"role":"user"},{"id":40,"role":"staff"}],"library":[],"triggers":[]}
